pyqt_hbounding_box/__init__.py
pyqt_hbounding_box/hboundingBox.py
pyqt_hbounding_box/item.py
pyqt_hbounding_box-0.0.13.dist-info/LICENSE
pyqt_hbounding_box-0.0.13.dist-info/METADATA
pyqt_hbounding_box-0.0.13.dist-info/WHEEL
pyqt_hbounding_box-0.0.13.dist-info/top_level.txt
pyqt_hbounding_box-0.0.13.dist-info/RECORD
