Metadata-Version: 2.1
Name: pyqt-hbounding-box
Version: 0.0.13
Summary: PyQt QGraphicsView with bounding box. User can move vertical border of the box horizontally.
Home-page: https://github.com/yjg30737/pyqt-hbounding-box.git
Author: Jung Gyu Yoon
Author-email: yjg30737@gmail.com
License: MIT
Platform: UNKNOWN
License-File: LICENSE
Requires-Dist: PyQt5 (>=5.8)
